[{"Valor":"15/03/2021","ExpresionRegular":"fecha","Resultado":"Cadena Valida"},{"Valor":"@yAsaLioComPI_1","ExpresionRegular":"igusername","Resultado":"Cadena Valida"},{"Valor":"hola#Mundo","ExpresionRegular":"erAzar","Resultado":"Cadena Valida"}]{"Valor":"primerexemakoa","ExpresionRegular":"ExpReg1","Resultado":"Cadena Valida"},{"Valor":"34.44","ExpresionRegular":"ExpresionReg2","Resultado":"Cadena Valida"}]{"Valor":"\'cadena entre comilla simple\'","ExpresionRegular":"EXP5","Resultado":"Cadena Valida"},{"Valor":"P-385fde","ExpresionRegular":"Pl","Resultado":"Cadena Valida"},{"Valor":"P388fdc","ExpresionRegular":"Pl","Resultado":"Cadena Valida"},{"Valor":"P38df8c","ExpresionRegular":"Pl","Resultado":"Cadena Valida"},{"Valor":"P-38df8k","ExpresionRegular":"Pl","Resultado":"Cadena Valida"},{"Valor":"K-385ffk","ExpresionRegular":"Pl","Resultado":"Cadena Valida"}]{"Valor":"301.59","ExpresionRegular":"decimales","Resultado":"Cadena Valida"},{"Valor":"1200.31","ExpresionRegular":"decimales","Resultado":"Cadena Valida"},{"Valor":"hola_soy_id_1","ExpresionRegular":"identificador","Resultado":"Cadena Valida"},{"Valor":"HoLA","ExpresionRegular":"identificador","Resultado":"Cadena Valida"}]{"Valor":"15/03/2021","ExpresionRegular":"fecha","Resultado":"Cadena Valida"},{"Valor":"@yAsaLioComPI_1","ExpresionRegular":"igusername","Resultado":"Cadena Valida"},{"Valor":"hola#Mundo","ExpresionRegular":"erAzar","Resultado":"Cadena Valida"}]
